nwae/ml/ModelBackTest.py
nwae/ml/ModelInterface.py
nwae/ml/ModelTemplate.py
nwae/ml/NwaeMlUnitTest.py
nwae/ml/PredictClass.py
nwae/ml/TrainingDataModel.py
nwae/ml/boosting/Boosting.py
nwae/ml/config/Config.py
nwae/ml/data/DataGenerator.py
nwae/ml/decisiontree/DecisionTree.py
nwae/ml/metricspace/MetricSpaceModel.py
nwae/ml/metricspace/ModelData.py
nwae/ml/metricspace/ut/UtMetricSpaceModel.py
nwae/ml/modelhelper/ModelHelper.py
nwae/ml/modelhelper/TextModelHelper.py
nwae/ml/networkdesign/NetworkDesign.py
nwae/ml/nndense/NnDenseModel.py
nwae/ml/nndense/NnDenseModelUnitTest.py
nwae/ml/sequence/SequenceModel.py
nwae/ml/text/EmbeddingParams.py
nwae/ml/text/TxtTransform.py
nwae/ml/text/preprocessing/TrDataPreprocessor.py
nwae/ml/text/preprocessing/TrDataPreprocessorUnitTest.py
nwae/ml/text/preprocessing/TrDataSampleData.py
nwae/ml/trainer/TextTrainer.py
nwae/ml/trainer/TrainUtils.py
nwae/ml/trainer/TrainerInterface.py
nwae.ml-0.3.5.dist-info/METADATA
nwae.ml-0.3.5.dist-info/WHEEL
nwae.ml-0.3.5.dist-info/top_level.txt
nwae.ml-0.3.5.dist-info/RECORD
