Metadata-Version: 2.1
Name: nwae.ml
Version: 0.3.5
Summary: ML
Home-page: UNKNOWN
Author: NWAE
Author-email: mapktah@ya.ru
License: UNKNOWN
Platform: UNKNOWN
Requires-Dist: nwae.utils
Requires-Dist: mex
Requires-Dist: nwae.lang
Requires-Dist: nwae.math
